nonebot_plugin_neuro_draw-0.1.0.dist-info/METADATA
nonebot_plugin_neuro_draw-0.1.0.dist-info/WHEEL
nonebot_plugin_neuro_draw-0.1.0.dist-info/entry_points.txt
nonebot_plugin_neuro_draw-0.1.0.dist-info/licenses/LICENSE
nonebot_plugin_neuro_draw/__init__.py
nonebot_plugin_neuro_draw-0.1.0.dist-info/RECORD
