Metadata-Version: 2.1
Name: nonebot-plugin-neuro-draw
Version: 0.1.0
Summary: ✨ Neuro 每日一签的 NoneBot 插件 ✨
Author-Email: zhaomaoniu <2667292003@qq.com>
License: MIT
Requires-Python: >=3.9
Requires-Dist: nonebot2>=2.4.1
Requires-Dist: nonebot-plugin-localstore>=0.7.3
Requires-Dist: nonebot-plugin-alconna>=0.54.2
Requires-Dist: aiohttp>=3.11.11
